pcontract/__init__.py
pcontract/data.py
pcontract/py.typed
pcontract/serialization.py
pcontract/backends/__init__.py
pcontract/backends/base.py
pcontract/backends/file.py
pcontract/backends/mongo.py
pcontract-1.0.0.dist-info/METADATA
pcontract-1.0.0.dist-info/WHEEL
pcontract-1.0.0.dist-info/licenses/LICENSE
pcontract-1.0.0.dist-info/RECORD
