Metadata-Version: 2.1
Name: pcontract
Version: 1.0.0
Summary: A data structure to track data over time.
Project-URL: Homepage, https://github.com/realsuayip/pcontract
Project-URL: Bug Tracker, https://github.com/realsuayip/pcontract/issues
Author-email: suayip uzulmez <suayip.541@gmail.com>
License: Copyright (c) 2022, Şuayip Üzülmez
License-File: LICENSE
Keywords: contract,contract-management,data-tracking
Classifier: License :: OSI Approved :: BSD License
Classifier: Programming Language :: Python
Classifier: Programming Language :: Python :: 3
Requires-Python: >=3.10
